Metadata-Version: 1.0
Name: splitres
Version: 1.5
Summary: Function calculates the min, max, average and sum of power consumption value and writes this data to a file.
Home-page: https://gitwork.ru/barabass/splitres.git
Author: German Borovkov
Author-email: UNKNOWN
License: UNKNOWN
Platform: UNKNOWN
